transformer_pack/__init__.py
transformer_pack/base.py
transformer_pack-0.1.0.dist-info/METADATA
transformer_pack-0.1.0.dist-info/WHEEL
transformer_pack-0.1.0.dist-info/top_level.txt
transformer_pack-0.1.0.dist-info/RECORD
